LICENSE
MANIFEST.in
README.rst
setup.py
sphero/__init__.py
sphero/core.py
sphero/request.py
sphero/response.py
sphero.egg-info/PKG-INFO
sphero.egg-info/SOURCES.txt
sphero.egg-info/dependency_links.txt
sphero.egg-info/not-zip-safe
sphero.egg-info/requires.txt
sphero.egg-info/top_level.txt