Metadata-Version: 1.0
Name: sphero
Version: 0.0.1
Summary: A python client for Sphero.
Home-page: http://github.com/faulkner/sphero
Author: Chris Faulkner
Author-email: thefaulkner@gmail.com
License: Copyright (c) 2012, Chris Faulkner
